gender_bench/__init__.py
gender_bench/config.py
gender_bench/generators/generator.py
gender_bench/generators/openai.py
gender_bench/generators/random.py
gender_bench/harnesses/default.py
gender_bench/probes/__init__.py
gender_bench/probes/bbq/bbq_evaluator.py
gender_bench/probes/bbq/bbq_metric_calculator.py
gender_bench/probes/bbq/bbq_probe.py
gender_bench/probes/business_vocabulary/business_vocabulary_evaluator.py
gender_bench/probes/business_vocabulary/business_vocabulary_metric_calculator.py
gender_bench/probes/business_vocabulary/business_vocabulary_probe.py
gender_bench/probes/direct/direct_metric_calculator.py
gender_bench/probes/direct/direct_probe.py
gender_bench/probes/discrimination_tamkin/discrimination_tamkin_genders.py
gender_bench/probes/discrimination_tamkin/discrimination_tamkin_metric_calculator.py
gender_bench/probes/discrimination_tamkin/discrimination_tamkin_probe.py
gender_bench/probes/diversity_med_qa/diversity_med_qa_evaluator.py
gender_bench/probes/diversity_med_qa/diversity_med_qa_metric_calculator.py
gender_bench/probes/diversity_med_qa/diversity_med_qa_probe.py
gender_bench/probes/dreaddit/dreaddit_metric_calculator.py
gender_bench/probes/dreaddit/dreaddit_probe.py
gender_bench/probes/generics/character_gender_evaluator.py
gender_bench/probes/generics/yes_no_evaluator.py
gender_bench/probes/gest/gest_evaluator.py
gender_bench/probes/gest/gest_metric_calculator.py
gender_bench/probes/gest/gest_probe.py
gender_bench/probes/gest/gest_templates.py
gender_bench/probes/gest_creative/gest_creative_metric_evaluator.py
gender_bench/probes/gest_creative/gest_creative_probe.py
gender_bench/probes/hiring_an/hiring_an_evaluator.py
gender_bench/probes/hiring_an/hiring_an_metric_calculator.py
gender_bench/probes/hiring_an/hiring_an_probe.py
gender_bench/probes/hiring_an/hiring_an_templates.py
gender_bench/probes/hiring_bloomberg/hiring_bloomberg_evaluator.py
gender_bench/probes/hiring_bloomberg/hiring_bloomberg_metric_calculator.py
gender_bench-0.4.0.dist-info/LICENSE
gender_bench-0.4.0.dist-info/METADATA
gender_bench-0.4.0.dist-info/WHEEL
gender_bench-0.4.0.dist-info/top_level.txt
gender_bench-0.4.0.dist-info/RECORD
