Metadata-Version: 2.2
Name: gender_bench
Version: 0.4.0
Summary: Evaluation suite for gender biases in LLMs.
Home-page: https://github.com/matus-pikuliak/gender_bench
Author: Matúš Pikuliak
Author-email: matus.pikuliak@gmail.com
License: See README
Project-URL: Documentation, https://gender-bench.readthedocs.io/en/latest/
Project-URL: Source Code, https://github.com/matus-pikuliak/gender_bench
Keywords: gender-bias fairness-ai llms llms-benchmarking
License-File: LICENSE
Requires-Dist: aiohttp==3.9.5
Requires-Dist: aiosignal==1.3.1
Requires-Dist: alabaster==1.0.0
Requires-Dist: annotated-types==0.7.0
Requires-Dist: anyio==4.4.0
Requires-Dist: asttokens==2.4.1
Requires-Dist: attrs==23.2.0
Requires-Dist: babel==2.16.0
Requires-Dist: build==1.2.2.post1
Requires-Dist: certifi==2024.7.4
Requires-Dist: cffi==1.17.1
Requires-Dist: charset-normalizer==3.3.2
Requires-Dist: click==8.1.7
Requires-Dist: comm==0.2.2
Requires-Dist: contourpy==1.2.1
Requires-Dist: cryptography==44.0.1
Requires-Dist: cycler==0.12.1
Requires-Dist: datasets==3.2.0
Requires-Dist: debugpy==1.8.2
Requires-Dist: decorator==5.1.1
Requires-Dist: dill==0.3.8
Requires-Dist: distro==1.9.0
Requires-Dist: docutils==0.21.2
Requires-Dist: executing==2.0.1
Requires-Dist: filelock==3.15.4
Requires-Dist: fonttools==4.53.1
Requires-Dist: frozenlist==1.4.1
Requires-Dist: fsspec==2024.5.0
Requires-Dist: gitdb==4.0.11
Requires-Dist: GitPython==3.1.41
Requires-Dist: h11==0.14.0
Requires-Dist: httpcore==1.0.5
Requires-Dist: httpx==0.27.0
Requires-Dist: huggingface-hub==0.27.0
Requires-Dist: id==1.5.0
Requires-Dist: idna==3.7
Requires-Dist: imagesize==1.4.1
Requires-Dist: ipykernel==6.29.5
Requires-Dist: ipython==8.26.0
Requires-Dist: isort==5.13.2
Requires-Dist: jaraco.classes==3.4.0
Requires-Dist: jaraco.context==6.0.1
Requires-Dist: jaraco.functools==4.1.0
Requires-Dist: jedi==0.19.1
Requires-Dist: jeepney==0.8.0
Requires-Dist: Jinja2==3.1.5
Requires-Dist: joblib==1.4.2
Requires-Dist: jupyter_client==8.6.2
Requires-Dist: jupyter_core==5.7.2
Requires-Dist: keyring==25.6.0
Requires-Dist: kiwisolver==1.4.5
Requires-Dist: markdown-it-py==3.0.0
Requires-Dist: MarkupSafe==3.0.2
Requires-Dist: matplotlib==3.9.1
Requires-Dist: matplotlib-inline==0.1.7
Requires-Dist: mdit-py-plugins==0.4.2
Requires-Dist: mdurl==0.1.2
Requires-Dist: mistune==3.1.0
Requires-Dist: more-itertools==10.6.0
Requires-Dist: multidict==6.0.5
Requires-Dist: multiprocess==0.70.16
Requires-Dist: myst-parser==4.0.0
Requires-Dist: nest-asyncio==1.6.0
Requires-Dist: nh3==0.2.20
Requires-Dist: nltk==3.8.1
Requires-Dist: numpy==2.0.0
Requires-Dist: openai==1.35.13
Requires-Dist: packaging==24.2
Requires-Dist: pandas==2.2.3
Requires-Dist: parso==0.8.4
Requires-Dist: pexpect==4.9.0
Requires-Dist: pillow==10.4.0
Requires-Dist: platformdirs==4.2.2
Requires-Dist: prompt_toolkit==3.0.47
Requires-Dist: psutil==6.0.0
Requires-Dist: ptyprocess==0.7.0
Requires-Dist: pure-eval==0.2.2
Requires-Dist: pyarrow==16.1.0
Requires-Dist: pyarrow-hotfix==0.6
Requires-Dist: pycparser==2.22
Requires-Dist: pydantic==2.8.2
Requires-Dist: pydantic_core==2.20.1
Requires-Dist: Pygments==2.18.0
Requires-Dist: pypandoc==1.15
Requires-Dist: pyparsing==3.1.2
Requires-Dist: pyproject_hooks==1.2.0
Requires-Dist: python-dateutil==2.9.0.post0
Requires-Dist: python-dotenv==1.0.1
Requires-Dist: pytz==2024.1
Requires-Dist: PyYAML==6.0.1
Requires-Dist: pyzmq==26.0.3
Requires-Dist: readme_renderer==44.0
Requires-Dist: regex==2024.5.15
Requires-Dist: requests==2.32.3
Requires-Dist: requests-toolbelt==1.0.0
Requires-Dist: rfc3986==2.0.0
Requires-Dist: rich==13.7.1
Requires-Dist: scikit-learn==1.5.1
Requires-Dist: scipy==1.14.0
Requires-Dist: SecretStorage==3.3.3
Requires-Dist: setuptools==75.8.0
Requires-Dist: six==1.16.0
Requires-Dist: smmap==5.0.1
Requires-Dist: sniffio==1.3.1
Requires-Dist: snowballstemmer==2.2.0
Requires-Dist: Sphinx==8.1.3
Requires-Dist: sphinx-rtd-theme==3.0.2
Requires-Dist: sphinx_mdinclude==0.6.2
Requires-Dist: sphinxcontrib-applehelp==2.0.0
Requires-Dist: sphinxcontrib-devhelp==2.0.0
Requires-Dist: sphinxcontrib-htmlhelp==2.1.0
Requires-Dist: sphinxcontrib-jquery==4.1
Requires-Dist: sphinxcontrib-jsmath==1.0.1
Requires-Dist: sphinxcontrib-qthelp==2.0.0
Requires-Dist: sphinxcontrib-serializinghtml==2.0.0
Requires-Dist: stack-data==0.6.3
Requires-Dist: threadpoolctl==3.5.0
Requires-Dist: tornado==6.4.1
Requires-Dist: tqdm==4.66.4
Requires-Dist: traitlets==5.14.3
Requires-Dist: twine==6.1.0
Requires-Dist: typing_extensions==4.12.2
Requires-Dist: tzdata==2024.1
Requires-Dist: urllib3==2.2.2
Requires-Dist: wcwidth==0.2.13
Requires-Dist: wheel==0.45.1
Requires-Dist: xxhash==3.4.1
Requires-Dist: yarl==1.9.4
Dynamic: author
Dynamic: author-email
Dynamic: description
Dynamic: description-content-type
Dynamic: home-page
Dynamic: keywords
Dynamic: license
Dynamic: project-url
Dynamic: requires-dist
Dynamic: summary
